recliner/__about__.py
recliner/__init__.py
recliner/__main__.py
recliner/renderer.py
recliner/six.py
recliner-0.2.1.data/scripts/recliner
recliner-0.2.1.dist-info/DESCRIPTION.rst
recliner-0.2.1.dist-info/entry_points.txt
recliner-0.2.1.dist-info/METADATA
recliner-0.2.1.dist-info/pydist.json
recliner-0.2.1.dist-info/RECORD
recliner-0.2.1.dist-info/top_level.txt
recliner-0.2.1.dist-info/WHEEL
