Metadata-Version: 2.0
Name: recliner
Version: 0.2.1
Summary: UNKNOWN
Home-page: https://github.com/crateio/recliner/
Author: Donald Stufft
Author-email: donald.stufft@gmail.com
License: Simplified BSD
Platform: UNKNOWN
Classifier: License :: OSI Approved :: BSD License
Classifier: Operating System :: POSIX
Classifier: Programming Language :: Python :: 2
Classifier: Programming Language :: Python :: 2.6
Classifier: Programming Language :: Python :: 2.7
Classifier: Programming Language :: Python :: 3
Classifier: Programming Language :: Python :: 3.3
Classifier: Programming Language :: Python :: Implementation :: CPython
Classifier: Programming Language :: Python :: Implementation :: PyPy
Requires-Dist: bleach (>=1.2)
Requires-Dist: docutils (>=0.9)
Requires-Dist: Pygments
Provides-Extra: tests
Requires-Dist: pep8; extra == 'tests'
Requires-Dist: pylint; extra == 'tests'
Requires-Dist: pytest; extra == 'tests'
Requires-Dist: pytest-cov; extra == 'tests'
